markdowngenerator/__init__.py
markdowngenerator/config/__init__.py
markdowngenerator/config/conf.py
markdowngenerator/config/syntax.py
markdowngenerator/markdowngenerator.py
markdowngenerator/test/__init__.py
markdowngenerator/test/test_blocks_quotes.py
markdowngenerator/test/test_markdown_emphasis.py
markdowngenerator/test/test_markdowngenerator_lib.py
markdowngenerator/test/test_references.py
python_markdown_generator-0.1.0.dist-info/LICENSE
python_markdown_generator-0.1.0.dist-info/METADATA
python_markdown_generator-0.1.0.dist-info/WHEEL
python_markdown_generator-0.1.0.dist-info/RECORD
