Metadata-Version: 2.1
Name: python-markdown-generator
Version: 0.1.0
Summary: Python library for dynamically generating HTML sanitized Markdown syntax.
Home-page: https://github.com/Nicceboy/python-markdown-generator
License: MIT
Author: Niklas Saari
Author-email: niklas.saari@tutanota.com
Requires-Python: >=3.7,<4.0
Classifier: License :: OSI Approved :: MIT License
Classifier: Programming Language :: Python :: 3
Classifier: Programming Language :: Python :: 3.7
Classifier: Programming Language :: Python :: 3.8
Classifier: Programming Language :: Python :: 3.9
Classifier: Programming Language :: Python :: 3.10
Classifier: Programming Language :: Python :: 3.11
Project-URL: Repository, https://github.com/Nicceboy/python-markdown-generator
